txb_api/__init__.py
txb_api/api.py
txb_api/client.py
txb_api/helpers.py
txb_api/public.py
txb_api-1.0.0.dist-info/DESCRIPTION.rst
txb_api-1.0.0.dist-info/METADATA
txb_api-1.0.0.dist-info/RECORD
txb_api-1.0.0.dist-info/WHEEL
txb_api-1.0.0.dist-info/metadata.json
txb_api-1.0.0.dist-info/top_level.txt
